README.md
setup.cfg
setup.py
UConnMLHI_UKBiobankProject/__init__.py
UConnMLHI_UKBiobankProject/main.py
UConnMLHI_UKBiobankProject.egg-info/PKG-INFO
UConnMLHI_UKBiobankProject.egg-info/SOURCES.txt
UConnMLHI_UKBiobankProject.egg-info/dependency_links.txt
UConnMLHI_UKBiobankProject.egg-info/top_level.txt
UConnMLHI_UKBiobankProject/Age_Prediction/Use_Lasso.py
UConnMLHI_UKBiobankProject/Age_Prediction/Use_RF.py
UConnMLHI_UKBiobankProject/Age_Prediction/Use_SVR.py
UConnMLHI_UKBiobankProject/Age_Prediction/__init__.py
UConnMLHI_UKBiobankProject/Data_Process/Data_Process.py
UConnMLHI_UKBiobankProject/Data_Process/__init__.py
UConnMLHI_UKBiobankProject/Utilities/Utilities.py
UConnMLHI_UKBiobankProject/Utilities/__init__.py